pdns_protobuf_receiver/__init__.py
pdns_protobuf_receiver/dnsmessage_pb2.py
pdns_protobuf_receiver/protobuf.py
pdns_protobuf_receiver/receiver.py
pdns_protobuf_receiver-1.0.1.dist-info/LICENSE
pdns_protobuf_receiver-1.0.1.dist-info/METADATA
pdns_protobuf_receiver-1.0.1.dist-info/WHEEL
pdns_protobuf_receiver-1.0.1.dist-info/entry_points.txt
pdns_protobuf_receiver-1.0.1.dist-info/top_level.txt
pdns_protobuf_receiver-1.0.1.dist-info/RECORD
