Metadata-Version: 2.1
Name: pdns-protobuf-receiver
Version: 1.0.1
Summary: Python PDNS protobuf receiver to JSON stream
Home-page: https://github.com/dmachard/pdns-protobuf-receiver
Author: Denis MACHARD
Author-email: d.machard@gmail.com
License: UNKNOWN
Keywords: protobuf pdns receiver json
Platform: any
Classifier: License :: OSI Approved :: MIT License
Classifier: Programming Language :: Python :: 3
Classifier: Operating System :: OS Independent
Classifier: Topic :: Software Development :: Libraries
Requires-Dist: dnspython
Requires-Dist: protobuf
